README.txt
bootstrap.py
buildout.cfg
setup.py
docs/HISTORY.txt
src/collective/__init__.py
src/collective.anonymousbrowser.egg-info/PKG-INFO
src/collective.anonymousbrowser.egg-info/SOURCES.txt
src/collective.anonymousbrowser.egg-info/dependency_links.txt
src/collective.anonymousbrowser.egg-info/namespace_packages.txt
src/collective.anonymousbrowser.egg-info/requires.txt
src/collective.anonymousbrowser.egg-info/top_level.txt
src/collective/anonymousbrowser/__init__.py
src/collective/anonymousbrowser/browser.py
src/collective/anonymousbrowser/real.py
src/collective/anonymousbrowser/tests/__init__.py
src/collective/anonymousbrowser/tests/browser.txt
src/collective/anonymousbrowser/tests/real.txt
src/collective/anonymousbrowser/tests/test_doctest_files.py
src/collective/anonymousbrowser/tests/utils.py