Metadata-Version: 1.0
Name: collective.anonymousbrowser
Version: 0.11
Summary: A zope.testbrowser extension with useragent faking and proxy abilitiesa sponsorised by Makina Corpus
Home-page: https://svn.plone.org/svn/collective/collective.anonymousbrowser/trunk
Author: Mathieu Pasquet
Author-email: kiorky@cryptelium.net
License: GPL
Platform: UNKNOWN
